adsmedia/__init__.py
adsmedia/client.py
adsmedia/types.py
adsmedia-1.0.0.dist-info/licenses/LICENSE
adsmedia-1.0.0.dist-info/METADATA
adsmedia-1.0.0.dist-info/WHEEL
adsmedia-1.0.0.dist-info/top_level.txt
adsmedia-1.0.0.dist-info/RECORD
