Metadata-Version: 2.4
Name: adsmedia
Version: 1.0.0
Summary: Official Python SDK for ADSMedia Email API
Home-page: https://github.com/ADSMedia-ai/ADSMedia
Author: ADSMedia
Author-email: ADSMedia <dev@adsmedia.ai>
License: MIT
Project-URL: Homepage, https://www.adsmedia.ai
Project-URL: Documentation, https://www.adsmedia.ai/api-docs
Project-URL: Repository, https://github.com/ADSMedia-ai/ADSMedia
Project-URL: Bug Tracker, https://github.com/ADSMedia-ai/ADSMedia/issues
Keywords: adsmedia,email,api,sdk,transactional,marketing
Classifier: Development Status :: 5 - Production/Stable
Classifier: Intended Audience :: Developers
Classifier: License :: OSI Approved :: MIT License
Classifier: Operating System :: OS Independent
Classifier: Programming Language :: Python :: 3
Classifier: Programming Language :: Python :: 3.8
Classifier: Programming Language :: Python :: 3.9
Classifier: Programming Language :: Python :: 3.10
Classifier: Programming Language :: Python :: 3.11
Classifier: Programming Language :: Python :: 3.12
Classifier: Topic :: Communications :: Email
Classifier: Topic :: Software Development :: Libraries :: Python Modules
Requires-Python: >=3.8
License-File: LICENSE
Requires-Dist: requests>=2.28.0
Provides-Extra: async
Requires-Dist: aiohttp>=3.8.0; extra == "async"
Provides-Extra: dev
Requires-Dist: pytest>=7.0.0; extra == "dev"
Requires-Dist: pytest-asyncio>=0.21.0; extra == "dev"
Requires-Dist: black>=23.0.0; extra == "dev"
Requires-Dist: mypy>=1.0.0; extra == "dev"
Requires-Dist: types-requests>=2.28.0; extra == "dev"
Dynamic: author
Dynamic: home-page
Dynamic: license-file
Dynamic: requires-python
